{
  "db_name": "PostgreSQL",
  "query": "\n            SELECT id, title, is_filter, is_primary_filter, filter_description,\n                default_filter_status, version, fill_color, border_color,\n                message_text, message_type AS \"message_type: AdmonitionType\"\n            FROM tags\n            ",
  "describe": {
    "columns": [
      {
        "ordinal": 0,
        "name": "id",
        "type_info": "Uuid"
      },
      {
        "ordinal": 1,
        "name": "title",
        "type_info": "Varchar"
      },
      {
        "ordinal": 2,
        "name": "is_filter",
        "type_info": "Bool"
      },
      {
        "ordinal": 3,
        "name": "is_primary_filter",
        "type_info": "Bool"
      },
      {
        "ordinal": 4,
        "name": "filter_description",
        "type_info": "Text"
      },
      {
        "ordinal": 5,
        "name": "default_filter_status",
        "type_info": "Bool"
      },
      {
        "ordinal": 6,
        "name": "version",
        "type_info": "Int4"
      },
      {
        "ordinal": 7,
        "name": "fill_color",
        "type_info": "Varchar"
      },
      {
        "ordinal": 8,
        "name": "border_color",
        "type_info": "Varchar"
      },
      {
        "ordinal": 9,
        "name": "message_text",
        "type_info": "Text"
      },
      {
        "ordinal": 10,
        "name": "message_type: AdmonitionType",
        "type_info": {
          "Custom": {
            "name": "admonition_type",
            "kind": {
              "Enum": [
                "neutral",
                "info",
                "success",
                "fail",
                "warning"
              ]
            }
          }
        }
      }
    ],
    "parameters": {
      "Left": []
    },
    "nullable": [
      false,
      false,
      false,
      false,
      true,
      false,
      false,
      false,
      false,
      true,
      true
    ]
  },
  "hash": "f35e103b9d75b127fd2da89267e8470e197e381a30b745df2d0f5950acc43b1d"
}
